twstock/__init__.py
twstock/__main__.py
twstock/analytics.py
twstock/legacy.py
twstock/proxy.py
twstock/realtime.py
twstock/stock.py
twstock/cli/__init__.py
twstock/cli/best_four_point.py
twstock/cli/realtime.py
twstock/cli/stock.py
twstock/codes/__init__.py
twstock/codes/codes.py
twstock/codes/fetch.py
twstock/codes/tpex_equities.csv
twstock/codes/twse_equities.csv
twstock/mock/__init__.py
twstock-1.3.1.dist-info/entry_points.txt
twstock-1.3.1.dist-info/LICENSE
twstock-1.3.1.dist-info/WHEEL
twstock-1.3.1.dist-info/METADATA
twstock-1.3.1.dist-info/RECORD
