Metadata-Version: 1.1
Name: twstock
Version: 1.3.1
Summary: Taiwan Stock Opendata with realtime - twstock
Home-page: https://github.com/mlouielu/twstock
Author: Louie Lu
Author-email: git@louie.lu
